conan/IMAP.json
conan/__init__.py
conan/config.py
conan/main.py
conan/utils.py
conan/web/index.html
conan/web/render.svg
conan/web/style.css
Conanmail-1.0.19.dist-info/METADATA
Conanmail-1.0.19.dist-info/WHEEL
Conanmail-1.0.19.dist-info/entry_points.txt
Conanmail-1.0.19.dist-info/top_level.txt
Conanmail-1.0.19.dist-info/RECORD
