Metadata-Version: 2.1
Name: Conanmail
Version: 1.0.19
Summary: Helping you delete your old accounts
Home-page: https://github.com/Gobutsu/Conan
Author: Gobutsu
Requires-Python: >=3.6
Requires-Dist: requests (==2.28.2)
Requires-Dist: jinja2 (==3.1.2)
Requires-Dist: tqdm (==4.65.0)
Requires-Dist: tldextract (==3.4.0)
